fb_logging/__init__.py
fb_logging/changelog.py
fb_logging/check_changelog.py
fb_logging/colored.py
fb_logging/dch2spl.py
fb_logging/deb_changelog.py
fb_logging/deb_version.py
fb_logging/syslog_handler.py
fb_logging/unix_handler.py
fb_logging-1.3.6.data/data/build/fb-logging.1.3.6
fb_logging-1.3.6.dist-info/entry_points.txt
fb_logging-1.3.6.dist-info/licenses/LICENSE
fb_logging-1.3.6.dist-info/WHEEL
fb_logging-1.3.6.dist-info/METADATA
fb_logging-1.3.6.dist-info/RECORD
